{
  "type": "FeatureCollection",
  "features": [

    {
      "type": "Feature",
      "properties": {
        "line": 13,
        "name": "chemin de hallage Est",
        "status": "done",
        "type": "voie-verte",
        "quality": "unsatisfactory",
        "link": "/rev-rennes-12#boulevard-pinel-à-bron-boutasse"
      },
      "geometry": {
        "type": "LineString",
        "coordinates": [
          [-1.674548328452606,48.12534284969198],
          [-1.674615615499641,48.1254541002047],
          [-1.674662836565247,48.125532556358245],
          [-1.674744499006244,48.12563313055195],
          [-1.674929023201275,48.125829091988194],
          [-1.675203434705735,48.126033744070774],
          [-1.675465759755068,48.12616743204242],
          [-1.675679199458211,48.12623950593967]
        ]
      }
    }
  ]
}
