{
  "type": "FeatureCollection",
  "features": [
    {
      "type": "Feature",
      "properties": {
        "line": 1,
        "name": "Rue de Saint-Malo",
        "status": "postponed",
        "type": "bandes-cyclables",
        "link": "/rev-rennes-1#rue-de-saint-malo-reporté"
      },
      "geometry": {
        "type": "LineString",
        "coordinates": [
[
            -1.6820661735761462,
            48.1208498827807
          ],
          [
            -1.6830244175916107,
            48.12146281111896
          ],
          [
            -1.6834616391957695,
            48.121900612597415
          ],
          [
            -1.6840838617643215,
            48.12244186739704
          ],
          [
            -1.68416037554573,
            48.12260725635309
          ],
          [
            -1.6842769679728065,
            48.12291614312423
          ],
          [
            -1.6844445695882655,
            48.123327178545395
          ],
          [
            -1.684600720401619,
            48.1235412822256
          ],
          [
            -1.684991541888877,
            48.124457385673225
          ],
          [
            -1.6855201322375706,
            48.125610606050344
          ],
          [
            -1.6856796243285999,
            48.12597157141826
          ],
          [
            -1.686113091314411,
            48.126624077331286
          ],
          [
            -1.6870126411009778,
            48.12803229714501
          ],
          [
            -1.6875065940072886,
            48.12865141974197
          ],
          [
            -1.6883942671192074,
            48.12937213533999
          ],
          [
            -1.6887037325406595,
            48.12973625579991
          ],
          [
            -1.68886456391985,
            48.129987332868126
          ],
          [
            -1.690222626518647,
            48.13132864738091
          ],
          [
            -1.6905827808635365,
            48.13179567992498
          ],
          [
            -1.6907908670667382,
            48.13213990938047
          ],
          [
            -1.6908211323692512,
            48.1323116852235
          ]
        ]
      }
    },
    {
      "type": "Feature",
      "properties": {
        "line": 1,
        "name": "Rue Saint-Malo au Boulevard de la Robiquette",
        "status": "done",
        "type": "bidirectionnelle",
	"quality": "satisfactory",
	"doneAt": "1/09/2025",
        "link": "/rev-rennes-1#rue-de-saint-malo-reporté"
      },
      "geometry": {
        "type": "LineString",
        "coordinates": [              
        [
            -1.6908211323692512,
            48.1323116852235
          ],
          [
            -1.6912250783022955,
            48.1322472643287
          ],
          [
            -1.6915551229995174,
            48.13205549933653
          ],
          [
            -1.6917881326154145,
            48.13225523771021
          ],
          [
            -1.691893561493913,
            48.13229741416404
          ],
          [
            -1.6919068565071314,
            48.132550999153494
          ],
          [
            -1.6920256106221814,
            48.13261833278278
          ]
         ]
      }
    },
    {
      "type": "Feature",
      "properties": {
        "id": "db-robiquette-rennes",
        "line": 1,
        "name": "Boulevard de la Robiquette",
        "status": "postponed",
        "type": "bandes-cyclables",
        "link": "/rev-rennes-1#rue-saint-malo-reporté"
      },
      "geometry": {
        "type": "LineString",
        "coordinates": [
                  [
            -1.6920256106221814,
            48.13261833278278
          ],
              [
            -1.6925709047452813,
            48.133074821422156
          ],
          [
            -1.6940384550813974,
            48.134073033900194
          ],
          [
            -1.695350082946078,
            48.1349844162105
          ],
          [
            -1.6964397771510278,
            48.13599645945561
          ],[
          -1.6971028691375807,
          48.13661537220537
        ],          [
            -1.6972285317264948,
            48.13656703110814
          ]
         ]
      }
    },
    {
      "type": "Feature",
      "properties": {
        "id": "derriere-grand-quartier",
        "line": 1,
        "name": "Derrière le centre commercial Grand Quartier",
        "status": "done",
        "type": "bidirectionnelle",
        "link": "/rev-rennes-1#boulevard-de-la-robiquette",
        "quality": "satisfactory"
      },
      "geometry": {
        "type": "LineString",
        "coordinates": [
           [
          -1.698843223782717,
          48.138939369587234
        ],
          [
            -1.6985946630394153,
            48.13859492111217
          ],
          [
            -1.6982339703514526,
            48.138055607549944
          ],
          [
            -1.6976768438114789,
            48.13707831712145
          ],
          [
            -1.69734893504733,
            48.13668739574146
          ],
          [
            -1.6972285317264948,
            48.13656703110814
          ]
        ]
      }
    },
    {
      "type": "Feature",
      "properties": {
        "id": "bd-robiquette-montgermont",
        "line": 1,
        "name": "Boulevard de la Robiquette (Montgermont)",
        "status": "done",
        "doneAt": "01/11/2022",
        "type": "bidirectionnelle",
        "link": "/rev-rennes-1#boulevard-de-la-robiquette",
        "quality": "satisfactory"
      },
      "geometry": {
        "type": "LineString",
        "coordinates": [
        [
          -1.698843223782717,
          48.138939369587234
        ],
          [
            -1.699045887668575,
            48.139201198655456
          ],
          [
            -1.6996159522221603,
            48.13985261956165
          ],
          [
            -1.7000029882695742,
            48.140257878477996
          ],
          [
            -1.7009658576227196,
            48.14126156480839
          ],
          [
            -1.7016083285446086,
            48.14206050324208
          ],
          [
            -1.701838499117855,
            48.142382923139024
          ],
          [
            -1.702047795678169,
            48.142776871779574
          ],
          [
            -1.7025256301047023,
            48.143792776672086
          ],
          [
            -1.702682767790435,
            48.14418587704074
          ],
          [
            -1.7028583712107377,
            48.14477957253311
          ],
          [
            -1.703183161797142,
            48.146071701389445
          ],
          [
            -1.7036956624914126,
            48.1479775069987
          ],
          [
            -1.7038987604896647,
            48.14859626763422
          ],
          [
            -1.7041153251689138,
            48.14904113208664
          ],
          [
            -1.7042169901288275,
            48.14930092593255
          ],
          [
            -1.7045495180867931,
            48.1499482780157
          ],
          [
            -1.7049184546209233,
            48.15060056806885
          ],
          [
            -1.7056303738815188,
            48.151640870941605
          ],
          [
            -1.7058048926389802,
            48.15184878047859
          ],
          [
            -1.705818036099373,
            48.15189210690639
          ],
          [
            -1.7057554173732967,
            48.15192883579172
          ],
          [
            -1.7057800770513438,
            48.151968552681126
          ],
          [
            -1.7058869775005974,
            48.1520299390377
          ],
          [
            -1.7060445394272392,
            48.15206110272035
          ],
          [
            -1.7061717767130062,
            48.152060945465905
          ]
        ]
      }
    },
      {
      "type": "Feature",
      "properties": {
        "id": "danger-d29-1",
        "type": "danger",
        "name": "Rond Point du Marais",
        "line": 1,
        "description" : "Deux voies à franchir puis une voie à franchir, priorité aux voitures",
        "danger": "Circulation automobile importante sur cet axe"
      },
      "geometry": {
        "coordinates": [-1.706257774048159, 48.15220896375841],
        "type": "Point"
      }
    },
    {
      "type": "Feature",
      "properties": {
        "id": "montgermont-giratoire",
        "line": 1,
        "name": "Rond Point du Marais",
        "status": "done",
        "doneAt": "01/11/2022",
        "type": "bidirectionnelle",
        "link": "/rev-rennes-1#montgermont",
        "quality": "unsatisfactory"
      },
      "geometry": {
        "type": "LineString",
        "coordinates": [
          [
            -1.7061717767130062,
            48.152060945465905
          ],
          [
            -1.7062644526186261,
            48.15220106326905
          ],
       [
            -1.7063857540589424,
            48.15232180747785
          ]
        ]
      }
    },
    {
      "type": "Feature",
      "properties": {
        "id": "montgermont-nord",
        "line": 1,
        "name": "Montgermont nord",
        "status": "expected",
        "type": "bidirectionnelle"
      },
      "geometry": {
        "type": "LineString",
        "coordinates": [
          [
            -1.7063857540589424,
            48.15232180747785
          ],
          [
            -1.7063502887820334,
            48.15242516749558
          ],
          [
            -1.7063502887820334,
            48.15261320747561
          ],
          [
            -1.7064958830749788,
            48.152852303673995
          ],
          [
            -1.7066746094100154,
            48.15315857901646
          ],
          [
            -1.706833269857725,
            48.15338023879883
          ],
          [
            -1.7069825973371167,
            48.153621821965146
          ],
          [
            -1.7072442688709941,
            48.154069833969885
          ],
          [
            -1.707890045938825,
            48.15520240226979
          ],
          [
            -1.7080318240869872,
            48.15542185885269
          ],
          [
            -1.708173685193458,
            48.15547291315215
          ],
          [
            -1.7082166168443678,
            48.155505289023154
          ],
          [
            -1.7082782144298108,
            48.155642263635684
          ]
        ]
      }
    },
    {
      "type": "Feature",
      "properties": {
        "line": 1,
        "name": "Liaison Pacé",
        "status": "expected",
        "type": "bidirectionnelle"
      },
      "geometry": {
        "type": "LineString",
        "coordinates": [
          [
            -1.7082760955820504,
            48.15564168905007
          ],
          [
            -1.7085523514209058,
            48.155596861034695
          ],
          [
            -1.7096498192202887,
            48.155355287174274
          ],
          [
            -1.710241529360303,
            48.15517597387722
          ],
          [
            -1.7104596698443117,
            48.15514857873319
          ],
          [
            -1.7105716654535854,
            48.155200878537585
          ],
          [
            -1.7106817944707302,
            48.155220802258555
          ],
          [
            -1.710849787885678,
            48.15517721910865
          ],
          [
            -1.7108945861298537,
            48.15512740974975
          ],
          [
            -1.7110856630797002,
            48.15514359779664
          ],
          [
            -1.7117520369599504,
            48.15526189490848
          ],
          [
            -1.7125677383195352,
            48.15536026808849
          ],
          [
            -1.713163053051943,
            48.15542114591108
          ],
          [
            -1.7144681928331238,
            48.15554317805592
          ],
          [
            -1.7147957799918458,
            48.15555438507499
          ],
          [
            -1.7149511531494568,
            48.155588628729646
          ],
          [
            -1.7151199357120106,
            48.15551105471198
          ],
          [
            -1.7153299274806955,
            48.1554307376189
          ],
          [
            -1.715412990891025,
            48.155440076822345
          ],
          [
            -1.71554085254661,
            48.15539773908691
          ],
          [
            -1.7155921838676136,
            48.15543011500537
          ],
          [
            -1.715963818482578,
            48.155376570205874
          ],
          [
            -1.7166619244521257,
            48.155417662731026
          ],
          [
            -1.7168365826322542,
            48.1553996069286
          ],
          [
            -1.7176868159726837,
            48.155387154647286
          ],
          [
            -1.7188102687985634,
            48.155460000450006
          ],
          [
            -1.7196116606315286,
            48.155506696422805
          ],
          [
            -1.7203988300634023,
            48.155658780414
          ],
          [
            -1.7210374072729735,
            48.155675590903996
          ],
          [
            -1.7214620572939907,
            48.15565815780346
          ],
          [
            -1.7227016257395462,
            48.15563823425251
          ],
          [
            -1.7238202814381225,
            48.15573349366156
          ],
          [
            -1.7257279482132617,
            48.15592836676677
          ],
          [
            -1.726372051537254,
            48.15598191099022
          ],
          [
            -1.7274086268837436,
            48.15598004316925
          ],
          [
            -1.7282625934095392,
            48.15604105861354
          ],
          [
            -1.7285416542996472,
            48.15603607776461
          ],
          [
            -1.7288655082719515,
            48.155989382273646
          ],
          [
            -1.728948571682281,
            48.15601055090144
          ],
          [
            -1.729883527602908,
            48.1558468051108
          ],
          [
            -1.730781403653225,
            48.15579824161907
          ],
          [
            -1.731028753204214,
            48.15575341374171
          ],
          [
            -1.7313488739853824,
            48.15561522325538
          ],
          [
            -1.7324606688953281,
            48.15493835097942
          ],
          [
            -1.7326425569919763,
            48.15487173064065
          ],
          [
            -1.7339668417793064,
            48.15469161523555
          ],
          [
            -1.7351775785951986,
            48.154293085419226
          ],
          [
            -1.7353375269914295,
            48.15418360457258
          ],
          [
            -1.7355073869879618,
            48.1536609424312
          ],
          [
            -1.7357203362662403,
            48.15342948354174
          ],
          [
            -1.7360637521395006,
            48.15325763519439
          ],
          [
            -1.7363130802819455,
            48.15320533340946
          ],
          [
            -1.7395744069170007,
            48.153148673082
          ],
          [
            -1.7396500039544094,
            48.15318105041959
          ],
          [
            -1.7398230216127502,
            48.153148673082
          ],
          [
            -1.7403190563863404,
            48.15312999383963
          ],
          [
            -1.7407337709440185,
            48.15306551580795
          ],
          [
            -1.7412554838274161,
            48.1528992700413
          ],
          [
            -1.7416133689099809,
            48.15272558656608
          ],
          [
            -1.7427478927366735,
            48.15200465931241
          ],
          [
            -1.7435002896036735,
            48.15152273024154
          ],
          [
            -1.7446708708052654,
            48.15076789000733
          ],
          [
            -1.744523106668396,
            48.15050205297126
          ],
          [
            -1.7443933066970203,
            48.150298689799314
          ],
          [
            -1.7443699718706966,
            48.1501585730781
          ],
          [
            -1.7446407206753065,
            48.150153194359746
          ],
          [
            -1.7461251008338081,
            48.150055647585475
          ],
          [
            -1.7503537602545691,
            48.14965864733685
          ],
          [
            -1.7511775346931984,
            48.14958440622348
          ],
          [
            -1.7525047029386371,
            48.14934892879279
          ],
          [
            -1.7537733007462748,
            48.148969178628676
          ],
          [
            -1.7551354712304033,
            48.148328903346936
          ],
          [
            -1.7556879783180932,
            48.14816340570533
          ],
          [
            -1.7559242434344355,
            48.14818870556948
          ],
          [
            -1.756122589457533,
            48.14817313642365
          ],
          [
            -1.7562188456166155,
            48.148151728840645
          ],
          [
            -1.7564201084934723,
            48.14795906018969
          ],
          [
            -1.7563938568133892,
            48.14784034480232
          ],
          [
            -1.7565717848638656,
            48.147676867426156
          ],
          [
            -1.7567817983009775,
            48.14757177455243
          ],
          [
            -1.7572484948262002,
            48.147310987602026
          ],
          [
            -1.759324234521472,
            48.146312719245145
          ],
          [
            -1.761086104679947,
            48.14555206613164
          ],
          [
            -1.761975744932272,
            48.145228988791644
          ],
          [
            -1.7622936819400081,
            48.145256236356204
          ],
          [
            -1.7626320369211612,
            48.14514919226741
          ],
          [
            -1.76270787510677,
            48.14496624367169
          ],
          [
            -1.7629571364111882,
            48.144808409979106
          ],
          [
            -1.7637767721844853,
            48.144502844505155
          ]
        ]
      }
    },
    {
      "type": "Feature",
      "properties": {
        "line": 1,
        "name": "Liaison Montgerval réseau CD35. Pas officiellement REV",
        "status": "expected",
        "type": "bidirectionnelle",
	"quality": "satisfactory",
	"link": "/rev-rennes-1#et-au-delà"
      },
      "geometry": {
        "type": "LineString",
        "coordinates": [
          [
            -1.708305463853435,
            48.15564916195592
          ],
          [
            -1.708238623356209,
            48.15574016170916
          ],
          [
            -1.7087337886783587,
            48.156485599317136
          ],
          [
            -1.709089816633906,
            48.156981537931046
          ],
          [
            -1.7094302909322607,
            48.157484033606096
          ],
          [
            -1.7098866918006763,
            48.15819371708466
          ],
          [
            -1.71035002224869,
            48.15891778498937
          ],
          [
            -1.710796713821594,
            48.159614692453516
          ],
          [
            -1.711445456175312,
            48.160623745159484
          ],
          [
            -1.712431614949196,
            48.16219319431292
          ],
          [
            -1.7127513083379142,
            48.16261034766083
          ],
          [
            -1.7142483543058518,
            48.16427660704002
          ],
          [
            -1.7165113761789996,
            48.16677077240206
          ],
          [
            -1.7175918378951565,
            48.16802844660597
          ],
          [
            -1.7184381921508987,
            48.16919986970734
          ],
          [
            -1.7193830003687367,
            48.1705959791928
          ],
          [
            -1.720165906405981,
            48.17177076216791
          ],
          [
            -1.7206878437640398,
            48.17261649256341
          ],
          [
            -1.7212025319929012,
            48.17371388116024
          ],
          [
            -1.7214062539678991,
            48.17392851839455
          ],
          [
            -1.7216202927380948,
            48.17404197539253
          ],
          [
            -1.7218535401160864,
            48.1740804043186
          ],
          [
            -1.7221334369701538,
            48.174084064214895
          ],
          [
            -1.7221444133174657,
            48.17421582030562
          ],
          [
            -1.7215912320731377,
            48.174722149498365
          ],
          [
            -1.7218701567040853,
            48.17585196530223
          ],
          [
            -1.722139393004369,
            48.17683796357554
          ],
          [
            -1.7226828980884932,
            48.178413105261455
          ],
          [
            -1.7229337465784056,
            48.179189656573016
          ],
          [
            -1.723094010897512,
            48.17933369148142
          ],
          [
            -1.723142786995254,
            48.17946843344862
          ],
          [
            -1.7230731068556224,
            48.17957065125648
          ],
          [
            -1.7233587954261225,
            48.180286170205136
          ],
          [
            -1.7238047483157288,
            48.18147093611583
          ],
          [
            -1.7240904368657652,
            48.18235373669688
          ],
          [
            -1.7244039974921748,
            48.183282929699686
          ],
          [
            -1.724640909963881,
            48.18376145752478
          ],
          [
            -1.724696654075558,
            48.18384043741602
          ],
          [
            -1.7247593662002316,
            48.18402162611832
          ],
          [
            -1.725205319089838,
            48.1848950395954
          ]
        ]
      }
    }

  ]
}
