{
  "name": "Place Bellecour",
  "description": "Ce compteur mesure le trafic sur Place Bellecour (Nord-Ouest).",
  "arrondissement": "Lyon 2",
  "idsPdc": [
    1365
  ],
  "coordinates": [
    4.830654,
    45.758873
  ],
  "cyclopolisId": "place-bellecour",
  "counts": [
    {
      "month": "2018-01-01",
      "count": 194525
    },
    {
      "month": "2018-02-01",
      "count": 182364
    },
    {
      "month": "2018-03-01",
      "count": 216101
    },
    {
      "month": "2018-04-01",
      "count": 200280
    },
    {
      "month": "2018-05-01",
      "count": 204817
    },
    {
      "month": "2018-06-01",
      "count": 212640
    },
    {
      "month": "2018-07-01",
      "count": 203484
    },
    {
      "month": "2018-08-01",
      "count": 180296
    },
    {
      "month": "2018-09-01",
      "count": 194550
    },
    {
      "month": "2018-10-01",
      "count": 205220
    },
    {
      "month": "2018-11-01",
      "count": 194400
    },
    {
      "month": "2018-12-01",
      "count": 190743
    },
    {
      "month": "2019-01-01",
      "count": 188356
    },
    {
      "month": "2019-02-01",
      "count": 170856
    },
    {
      "month": "2019-03-01",
      "count": 283092
    },
    {
      "month": "2019-04-01",
      "count": 299490
    },
    {
      "month": "2019-05-01",
      "count": 307489
    },
    {
      "month": "2019-06-01",
      "count": 325050
    },
    {
      "month": "2019-07-01",
      "count": 351819
    },
    {
      "month": "2019-08-01",
      "count": 319424
    },
    {
      "month": "2019-09-01",
      "count": 312660
    },
    {
      "month": "2019-10-01",
      "count": 193905
    },
    {
      "month": "2019-11-01",
      "count": 188280
    },
    {
      "month": "2019-12-01",
      "count": 182063
    },
    {
      "month": "2020-01-01",
      "count": 174220
    },
    {
      "month": "2020-02-01",
      "count": 232522
    },
    {
      "month": "2020-03-01",
      "count": 185287
    },
    {
      "month": "2020-04-01",
      "count": 63810
    },
    {
      "month": "2020-05-01",
      "count": 193440
    },
    {
      "month": "2020-06-01",
      "count": 299940
    },
    {
      "month": "2020-07-01",
      "count": 233647
    },
    {
      "month": "2020-08-01",
      "count": 270041
    },
    {
      "month": "2020-09-01",
      "count": 274410
    },
    {
      "month": "2020-10-01",
      "count": 254355
    },
    {
      "month": "2020-11-01",
      "count": 140580
    },
    {
      "month": "2020-12-01",
      "count": 227633
    },
    {
      "month": "2021-01-01",
      "count": 204910
    },
    {
      "month": "2021-02-01",
      "count": 202356
    },
    {
      "month": "2021-03-01",
      "count": 220689
    },
    {
      "month": "2021-04-01",
      "count": 174360
    },
    {
      "month": "2021-05-01",
      "count": 234670
    },
    {
      "month": "2021-06-01",
      "count": 287250
    },
    {
      "month": "2021-07-01",
      "count": 302591
    },
    {
      "month": "2021-08-01",
      "count": 258757
    },
    {
      "month": "2021-09-01",
      "count": 293490
    },
    {
      "month": "2021-10-01",
      "count": 307210
    },
    {
      "month": "2021-11-01",
      "count": 274350
    },
    {
      "month": "2021-12-01",
      "count": 267623
    },
    {
      "month": "2022-01-01",
      "count": 246543
    },
    {
      "month": "2022-02-01",
      "count": 250740
    },
    {
      "month": "2022-03-01",
      "count": 285386
    },
    {
      "month": "2022-04-01",
      "count": 261930
    },
    {
      "month": "2022-05-01",
      "count": 280023
    },
    {
      "month": "2022-06-01",
      "count": 282240
    },
    {
      "month": "2022-07-01",
      "count": 278535
    },
    {
      "month": "2022-08-01",
      "count": 246140
    },
    {
      "month": "2022-09-01",
      "count": 261480
    },
    {
      "month": "2022-10-01",
      "count": 254355
    },
    {
      "month": "2022-11-01",
      "count": 238920
    },
    {
      "month": "2022-12-01",
      "count": 237677
    },
    {
      "month": "2023-01-01",
      "count": 233337
    },
    {
      "month": "2023-02-01",
      "count": 203840
    },
    {
      "month": "2023-03-01",
      "count": 233864
    },
    {
      "month": "2023-04-01",
      "count": 220770
    },
    {
      "month": "2023-05-01",
      "count": 237181
    },
    {
      "month": "2023-06-01",
      "count": 226110
    },
    {
      "month": "2023-07-01",
      "count": 214334
    },
    {
      "month": "2023-08-01",
      "count": 179707
    },
    {
      "month": "2023-09-01",
      "count": 209520
    },
    {
      "month": "2023-10-01",
      "count": 216132
    },
    {
      "month": "2023-11-01",
      "count": 218160
    },
    {
      "month": "2023-12-01",
      "count": 236654
    },
    {
      "month": "2024-01-01",
      "count": 172112
    },
    {
      "month": "2024-02-01",
      "count": 163937
    },
    {
      "month": "2024-03-01",
      "count": 181567
    },
    {
      "month": "2024-04-01",
      "count": 179100
    },
    {
      "month": "2024-05-01",
      "count": 173321
    },
    {
      "month": "2024-06-01",
      "count": 175110
    },
    {
      "month": "2024-07-01",
      "count": 169105
    },
    {
      "month": "2024-08-01",
      "count": 153109
    },
    {
      "month": "2024-09-01",
      "count": 166650
    },
    {
      "month": "2024-10-01",
      "count": 192138
    },
    {
      "month": "2024-11-01",
      "count": 173880
    },
    {
      "month": "2024-12-01",
      "count": 160890
    },
    {
      "month": "2025-01-01",
      "count": 163742
    },
    {
      "month": "2025-02-01",
      "count": 221284
    },
    {
      "month": "2025-03-01",
      "count": 309814
    },
    {
      "month": "2025-04-01",
      "count": 290130
    },
    {
      "month": "2025-05-01",
      "count": 300793
    }
  ]
}